{
  "version": 2,
  "extractor": "papercropper",
  "figures": [
    {
      "url": "assets/figures/arxiv/2606.22570v1/fig-001.webp",
      "caption": "",
      "page": 0,
      "index": 1,
      "width": 1158,
      "height": 508,
      "label": "Figure"
    },
    {
      "url": "assets/figures/arxiv/2606.22570v1/fig-002.webp",
      "caption": "",
      "page": 0,
      "index": 2,
      "width": 1447,
      "height": 601,
      "label": "Figure"
    },
    {
      "url": "assets/figures/arxiv/2606.22570v1/fig-003.webp",
      "caption": "",
      "page": 0,
      "index": 3,
      "width": 1008,
      "height": 496,
      "label": "Figure"
    },
    {
      "url": "assets/figures/arxiv/2606.22570v1/fig-004.webp",
      "caption": "",
      "page": 0,
      "index": 4,
      "width": 720,
      "height": 588,
      "label": "Figure"
    },
    {
      "url": "assets/figures/arxiv/2606.22570v1/fig-005.webp",
      "caption": "",
      "page": 0,
      "index": 5,
      "width": 451,
      "height": 498,
      "label": "Figure"
    },
    {
      "url": "assets/figures/arxiv/2606.22570v1/fig-006.webp",
      "caption": "",
      "page": 0,
      "index": 6,
      "width": 1352,
      "height": 409,
      "label": "Figure"
    },
    {
      "url": "assets/figures/arxiv/2606.22570v1/fig-007.webp",
      "caption": "",
      "page": 0,
      "index": 7,
      "width": 1438,
      "height": 954,
      "label": "Figure"
    }
  ]
}