{
  "version": 2,
  "extractor": "papercropper",
  "figures": [
    {
      "url": "assets/figures/arxiv/2606.17735v1/fig-001.webp",
      "caption": "",
      "page": 0,
      "index": 1,
      "width": 1390,
      "height": 395,
      "label": "Figure"
    },
    {
      "url": "assets/figures/arxiv/2606.17735v1/fig-002.webp",
      "caption": "",
      "page": 0,
      "index": 2,
      "width": 1386,
      "height": 569,
      "label": "Figure"
    },
    {
      "url": "assets/figures/arxiv/2606.17735v1/fig-003.webp",
      "caption": "",
      "page": 0,
      "index": 3,
      "width": 1375,
      "height": 308,
      "label": "Figure"
    },
    {
      "url": "assets/figures/arxiv/2606.17735v1/fig-004.webp",
      "caption": "",
      "page": 0,
      "index": 4,
      "width": 1394,
      "height": 410,
      "label": "Figure"
    },
    {
      "url": "assets/figures/arxiv/2606.17735v1/fig-005.webp",
      "caption": "",
      "page": 0,
      "index": 5,
      "width": 1378,
      "height": 307,
      "label": "Figure"
    },
    {
      "url": "assets/figures/arxiv/2606.17735v1/fig-006.webp",
      "caption": "",
      "page": 0,
      "index": 6,
      "width": 1419,
      "height": 1829,
      "label": "Figure"
    }
  ]
}