{
  "version": 2,
  "extractor": "papercropper",
  "tables": [
    {
      "url": "assets/tables/arxiv/2606.22142v1/table-001.webp",
      "caption": "",
      "page": 0,
      "index": 1,
      "width": 824,
      "height": 478,
      "label": "Table"
    },
    {
      "url": "assets/tables/arxiv/2606.22142v1/table-002.webp",
      "caption": "",
      "page": 0,
      "index": 2,
      "width": 735,
      "height": 224,
      "label": "Table"
    },
    {
      "url": "assets/tables/arxiv/2606.22142v1/table-003.webp",
      "caption": "",
      "page": 0,
      "index": 3,
      "width": 909,
      "height": 221,
      "label": "Table"
    },
    {
      "url": "assets/tables/arxiv/2606.22142v1/table-004.webp",
      "caption": "",
      "page": 0,
      "index": 4,
      "width": 1440,
      "height": 1136,
      "label": "Table"
    },
    {
      "url": "assets/tables/arxiv/2606.22142v1/table-005.webp",
      "caption": "",
      "page": 0,
      "index": 5,
      "width": 1402,
      "height": 546,
      "label": "Table"
    },
    {
      "url": "assets/tables/arxiv/2606.22142v1/table-006.webp",
      "caption": "",
      "page": 0,
      "index": 6,
      "width": 1429,
      "height": 574,
      "label": "Table"
    },
    {
      "url": "assets/tables/arxiv/2606.22142v1/table-007.webp",
      "caption": "",
      "page": 0,
      "index": 7,
      "width": 1416,
      "height": 317,
      "label": "Table"
    },
    {
      "url": "assets/tables/arxiv/2606.22142v1/table-008.webp",
      "caption": "",
      "page": 0,
      "index": 8,
      "width": 1412,
      "height": 459,
      "label": "Table"
    },
    {
      "url": "assets/tables/arxiv/2606.22142v1/table-009.webp",
      "caption": "",
      "page": 0,
      "index": 9,
      "width": 1446,
      "height": 547,
      "label": "Table"
    },
    {
      "url": "assets/tables/arxiv/2606.22142v1/table-010.webp",
      "caption": "",
      "page": 0,
      "index": 10,
      "width": 1320,
      "height": 231,
      "label": "Table"
    },
    {
      "url": "assets/tables/arxiv/2606.22142v1/table-011.webp",
      "caption": "",
      "page": 0,
      "index": 11,
      "width": 1195,
      "height": 143,
      "label": "Table"
    },
    {
      "url": "assets/tables/arxiv/2606.22142v1/table-012.webp",
      "caption": "",
      "page": 0,
      "index": 12,
      "width": 1451,
      "height": 251,
      "label": "Table"
    },
    {
      "url": "assets/tables/arxiv/2606.22142v1/table-013.webp",
      "caption": "",
      "page": 0,
      "index": 13,
      "width": 1234,
      "height": 306,
      "label": "Table"
    },
    {
      "url": "assets/tables/arxiv/2606.22142v1/table-014.webp",
      "caption": "",
      "page": 0,
      "index": 14,
      "width": 1551,
      "height": 771,
      "label": "Table"
    },
    {
      "url": "assets/tables/arxiv/2606.22142v1/table-015.webp",
      "caption": "",
      "page": 0,
      "index": 15,
      "width": 1224,
      "height": 201,
      "label": "Table"
    }
  ]
}