{
  "version": 2,
  "extractor": "papercropper",
  "figures": [
    {
      "url": "assets/figures/arxiv/2606.23664v1/fig-001.webp",
      "caption": "",
      "page": 0,
      "index": 1,
      "width": 1633,
      "height": 625,
      "label": "Figure"
    },
    {
      "url": "assets/figures/arxiv/2606.23664v1/fig-002.webp",
      "caption": "",
      "page": 0,
      "index": 2,
      "width": 1663,
      "height": 504,
      "label": "Figure"
    },
    {
      "url": "assets/figures/arxiv/2606.23664v1/fig-003.webp",
      "caption": "",
      "page": 0,
      "index": 3,
      "width": 1692,
      "height": 586,
      "label": "Figure"
    },
    {
      "url": "assets/figures/arxiv/2606.23664v1/fig-004.webp",
      "caption": "",
      "page": 0,
      "index": 4,
      "width": 1629,
      "height": 750,
      "label": "Figure"
    },
    {
      "url": "assets/figures/arxiv/2606.23664v1/fig-005.webp",
      "caption": "",
      "page": 0,
      "index": 5,
      "width": 1638,
      "height": 731,
      "label": "Figure"
    },
    {
      "url": "assets/figures/arxiv/2606.23664v1/fig-006.webp",
      "caption": "",
      "page": 0,
      "index": 6,
      "width": 1633,
      "height": 755,
      "label": "Figure"
    }
  ]
}