{
  "version": 2,
  "extractor": "papercropper",
  "tables": [
    {
      "url": "assets/tables/arxiv/2606.23155v1/table-001.webp",
      "caption": "",
      "page": 0,
      "index": 1,
      "width": 1445,
      "height": 546,
      "label": "Table"
    },
    {
      "url": "assets/tables/arxiv/2606.23155v1/table-002.webp",
      "caption": "",
      "page": 0,
      "index": 2,
      "width": 917,
      "height": 538,
      "label": "Table"
    },
    {
      "url": "assets/tables/arxiv/2606.23155v1/table-003.webp",
      "caption": "",
      "page": 0,
      "index": 3,
      "width": 1446,
      "height": 241,
      "label": "Table"
    },
    {
      "url": "assets/tables/arxiv/2606.23155v1/table-004.webp",
      "caption": "",
      "page": 0,
      "index": 4,
      "width": 1456,
      "height": 562,
      "label": "Table"
    },
    {
      "url": "assets/tables/arxiv/2606.23155v1/table-005.webp",
      "caption": "",
      "page": 0,
      "index": 5,
      "width": 1439,
      "height": 713,
      "label": "Table"
    },
    {
      "url": "assets/tables/arxiv/2606.23155v1/table-006.webp",
      "caption": "",
      "page": 0,
      "index": 6,
      "width": 1402,
      "height": 542,
      "label": "Table"
    },
    {
      "url": "assets/tables/arxiv/2606.23155v1/table-007.webp",
      "caption": "",
      "page": 0,
      "index": 7,
      "width": 1708,
      "height": 387,
      "label": "Table"
    }
  ]
}